businesscommunications/__init__.py
businesscommunications/businesscommunications_v1_client.py
businesscommunications/businesscommunications_v1_messages.py
google_businesscommunications-2.1.0.dist-info/LICENSE
google_businesscommunications-2.1.0.dist-info/METADATA
google_businesscommunications-2.1.0.dist-info/WHEEL
google_businesscommunications-2.1.0.dist-info/top_level.txt
google_businesscommunications-2.1.0.dist-info/RECORD
